[
{"id":32665718,"full_name":"shockone/black-screen","html_url":"https://github.com/shockone/black-screen","description":"A terminal emulator for the 21st century.","created_at":"2015-03-22 07:00:24 UTC","language":"TypeScript","watchers_count":8464,"network_count":204,"daily_watchers_count":626},
{"id":28457823,"full_name":"FreeCodeCamp/FreeCodeCamp","html_url":"https://github.com/FreeCodeCamp/FreeCodeCamp","description":"The https://FreeCodeCamp.com open source codebase and curriculum. Learn to code and help nonprofits.","created_at":"2014-12-24 17:49:19 UTC","language":"JavaScript","watchers_count":126330,"network_count":4486,"daily_watchers_count":502},
{"id":58836534,"full_name":"parkjs814/AlgorithmVisualizer","html_url":"https://github.com/parkjs814/AlgorithmVisualizer","description":"Algorithm Visualizer","created_at":"2016-05-15 00:27:45 UTC","language":"JavaScript","watchers_count":504,"network_count":91,"daily_watchers_count":429},
{"id":55584626,"full_name":"eliangcs/http-prompt","html_url":"https://github.com/eliangcs/http-prompt","description":"HTTPie + prompt_toolkit = an interactive command-line HTTP client featuring autocomplete and syntax highlighting","created_at":"2016-04-06 07:24:35 UTC","language":"Python","watchers_count":2705,"network_count":65,"daily_watchers_count":287},
{"id":58327877,"full_name":"tombh/texttop","html_url":"https://github.com/tombh/texttop","description":"A fully interactive X linux desktop rendered to ASCII and streamed over SSH","created_at":"2016-05-08 19:34:15 UTC","language":"Go","watchers_count":491,"network_count":12,"daily_watchers_count":242},
{"id":39357088,"full_name":"Nickersoft/push.js","html_url":"https://github.com/Nickersoft/push.js","description":"A compact, cross-browser solution for using the JavaScript Notifications API","created_at":"2015-07-20 01:46:04 UTC","language":"JavaScript","watchers_count":3259,"network_count":78,"daily_watchers_count":225},
{"id":58905085,"full_name":"rishabhp/bideo.js","html_url":"https://github.com/rishabhp/bideo.js","description":"Fullscreen HTML5 Background Video for the Web.","created_at":"2016-05-16 05:05:42 UTC","language":"JavaScript","watchers_count":243,"network_count":7,"daily_watchers_count":212},
{"id":34088285,"full_name":"andlabs/libui","html_url":"https://github.com/andlabs/libui","description":"Simple and portable (but not inflexible) GUI library in C that uses the native GUI technologies of each platform it supports.","created_at":"2015-04-17 00:35:54 UTC","language":"C","watchers_count":2637,"network_count":107,"daily_watchers_count":198},
{"id":48716639,"full_name":"sitespeedio/coach","html_url":"https://github.com/sitespeedio/coach","description":"Clear Eyes. Full Hearts. Can’t Lose.","created_at":"2015-12-28 23:08:49 UTC","language":"JavaScript","watchers_count":510,"network_count":15,"daily_watchers_count":171},
{"id":14194174,"full_name":"alex/what-happens-when","html_url":"https://github.com/alex/what-happens-when","description":"An attempt to answer the age old interview question \"What happens when you type google.com into your browser and press enter?\"","created_at":"2013-11-07 04:30:06 UTC","language":null,"watchers_count":10995,"network_count":752,"daily_watchers_count":166},
{"id":59155443,"full_name":"Netflix/bless","html_url":"https://github.com/Netflix/bless","description":"Repository for BLESS, an SSH Certificate Authority that runs as a AWS Lambda function","created_at":"2016-05-18 22:19:30 UTC","language":"Python","watchers_count":305,"network_count":11,"daily_watchers_count":166},
{"id":59257993,"full_name":"hwdsl2/docker-ipsec-vpn-server","html_url":"https://github.com/hwdsl2/docker-ipsec-vpn-server","description":"IPsec VPN server on Docker, with both IPsec/L2TP and Cisco IPsec","created_at":"2016-05-20 02:19:32 UTC","language":"Shell","watchers_count":179,"network_count":7,"daily_watchers_count":151},
{"id":30794868,"full_name":"Selz/plyr","html_url":"https://github.com/Selz/plyr","description":"A simple HTML5, YouTube and Vimeo player","created_at":"2015-02-14 11:33:07 UTC","language":"JavaScript","watchers_count":6969,"network_count":485,"daily_watchers_count":138},
{"id":45091124,"full_name":"rethinkdb/horizon","html_url":"https://github.com/rethinkdb/horizon","description":"Horizon is a realtime, open-source backend for JavaScript apps.","created_at":"2015-10-28 05:33:14 UTC","language":"JavaScript","watchers_count":3279,"network_count":80,"daily_watchers_count":135},
{"id":58783726,"full_name":"cutestrap/cutestrap","html_url":"https://github.com/cutestrap/cutestrap","description":"","created_at":"2016-05-14 01:39:55 UTC","language":"CSS","watchers_count":561,"network_count":28,"daily_watchers_count":135},
{"id":30969188,"full_name":"mxstbr/react-boilerplate","html_url":"https://github.com/mxstbr/react-boilerplate","description":":fire: A highly scalable, offline-first foundation with the best developer experience and a focus on performance and best practices.","created_at":"2015-02-18 14:36:32 UTC","language":"JavaScript","watchers_count":6401,"network_count":387,"daily_watchers_count":135},
{"id":54576330,"full_name":"phodal/growth-in-action","html_url":"https://github.com/phodal/growth-in-action","description":"全栈增长工程师实战","created_at":"2016-03-23 16:36:49 UTC","language":"HTML","watchers_count":323,"network_count":65,"daily_watchers_count":134},
{"id":59376841,"full_name":"LukyVj/family.scss","html_url":"https://github.com/LukyVj/family.scss","description":"","created_at":"2016-05-21 19:00:23 UTC","language":"CSS","watchers_count":138,"network_count":7,"daily_watchers_count":124},
{"id":45461509,"full_name":"jobbole/awesome-javascript-cn","html_url":"https://github.com/jobbole/awesome-javascript-cn","description":"JavaScript 资源大全中文版，内容包括：包管理器、加载器、测试框架、运行器、QA、MVC框架和库、模板引擎等","created_at":"2015-11-03 11:17:05 UTC","language":null,"watchers_count":1235,"network_count":397,"daily_watchers_count":106},
{"id":22660515,"full_name":"onqtam/doctest","html_url":"https://github.com/onqtam/doctest","description":"The lightest feature rich C++ single header testing framework for unit tests and TDD - docs:","created_at":"2014-08-05 21:43:51 UTC","language":"C++","watchers_count":115,"network_count":6,"daily_watchers_count":104},
{"id":54360307,"full_name":"alexhultman/uWebSockets","html_url":"https://github.com/alexhultman/uWebSockets","description":"Highly scalable WebSocket server library","created_at":"2016-03-21 04:39:40 UTC","language":"C++","watchers_count":1465,"network_count":52,"daily_watchers_count":103},
{"id":12892446,"full_name":"madmalik/mononoki","html_url":"https://github.com/madmalik/mononoki","description":"a programming typeface","created_at":"2013-09-17 10:26:12 UTC","language":"CSS","watchers_count":2155,"network_count":121,"daily_watchers_count":98},
{"id":43759462,"full_name":"ujjwalkarn/DataSciencePython","html_url":"https://github.com/ujjwalkarn/DataSciencePython","description":"common data analysis and machine learning tasks using python","created_at":"2015-10-06 15:26:08 UTC","language":"Python","watchers_count":1309,"network_count":172,"daily_watchers_count":93},
{"id":23693362,"full_name":"yourtion/30dayMakeOS","html_url":"https://github.com/yourtion/30dayMakeOS","description":"《30天自制操作系统》源码中文版。自己制作一个操作系统（OSASK）的过程","created_at":"2014-09-05 06:54:36 UTC","language":"C","watchers_count":238,"network_count":48,"daily_watchers_count":92},
{"id":59015890,"full_name":"joshnewlan/say_what","html_url":"https://github.com/joshnewlan/say_what","description":"Using speech-to-text to fully check out during con calls","created_at":"2016-05-17 11:17:46 UTC","language":"Python","watchers_count":326,"network_count":31,"daily_watchers_count":92},
{"id":42408804,"full_name":"containous/traefik","html_url":"https://github.com/containous/traefik","description":"Træfɪk, a modern reverse proxy","created_at":"2015-09-13 19:04:02 UTC","language":"Go","watchers_count":2762,"network_count":169,"daily_watchers_count":88},
{"id":53370988,"full_name":"GoogleChrome/lighthouse","html_url":"https://github.com/GoogleChrome/lighthouse","description":"auditing and performance metrics for Progressive Web Apps","created_at":"2016-03-08 01:03:11 UTC","language":"JavaScript","watchers_count":322,"network_count":18,"daily_watchers_count":88},
{"id":1999522,"full_name":"nlp-compromise/nlp_compromise","html_url":"https://github.com/nlp-compromise/nlp_compromise","description":"a cool way to use natural language in javascript","created_at":"2011-07-05 09:04:38 UTC","language":"JavaScript","watchers_count":5118,"network_count":227,"daily_watchers_count":87},
{"id":38226908,"full_name":"nvdv/vprof","html_url":"https://github.com/nvdv/vprof","description":"Visual Python profiler","created_at":"2015-06-29 03:59:39 UTC","language":"Python","watchers_count":2280,"network_count":83,"daily_watchers_count":86},
{"id":59345600,"full_name":"hilongjw/vue-zhihu-daily","html_url":"https://github.com/hilongjw/vue-zhihu-daily","description":"zhihu daily spa with vue  线上演示在这里 ---->","created_at":"2016-05-21 06:32:55 UTC","language":"Vue","watchers_count":103,"network_count":10,"daily_watchers_count":77},
{"id":56897766,"full_name":"donnemartin/gitsome","html_url":"https://github.com/donnemartin/gitsome","description":"A supercharged Git/shell autocompleter with GitHub integration.","created_at":"2016-04-23 03:08:21 UTC","language":"Python","watchers_count":2635,"network_count":68,"daily_watchers_count":70},
{"id":5483330,"full_name":"soimort/you-get","html_url":"https://github.com/soimort/you-get","description":":arrow_double_down: Dumb downloader that scrapes the web","created_at":"2012-08-20 15:53:36 UTC","language":"Python","watchers_count":6200,"network_count":1088,"daily_watchers_count":68},
{"id":9384267,"full_name":"electron/electron","html_url":"https://github.com/electron/electron","description":"Build cross platform desktop apps with JavaScript, HTML, and CSS","created_at":"2013-04-12 01:47:36 UTC","language":"C++","watchers_count":29935,"network_count":3105,"daily_watchers_count":66},
{"id":55238527,"full_name":"JoelOtter/kajero","html_url":"https://github.com/JoelOtter/kajero","description":"Interactive JavaScript notebooks with clever graphing","created_at":"2016-04-01 14:31:41 UTC","language":"JavaScript","watchers_count":1140,"network_count":44,"daily_watchers_count":63},
{"id":59152263,"full_name":"sindresorhus/fast-cli","html_url":"https://github.com/sindresorhus/fast-cli","description":"Test your download speed using fast.com","created_at":"2016-05-18 21:24:15 UTC","language":"JavaScript","watchers_count":283,"network_count":3,"daily_watchers_count":63},
{"id":12537898,"full_name":"BYVoid/Batsh","html_url":"https://github.com/BYVoid/Batsh","description":"A language that compiles to Bash and Windows Batch","created_at":"2013-09-02 10:45:45 UTC","language":"OCaml","watchers_count":2983,"network_count":141,"daily_watchers_count":60},
{"id":25237608,"full_name":"andkulikov/Transitions-Everywhere","html_url":"https://github.com/andkulikov/Transitions-Everywhere","description":"Backport of Android Transitions API for animations. Animations backported to Android 4.0+. API compatible with Android 2.2+","created_at":"2014-10-15 03:37:03 UTC","language":"Java","watchers_count":1226,"network_count":127,"daily_watchers_count":59},
{"id":59254072,"full_name":"EnjoySR/ESTranslate-Xcode","html_url":"https://github.com/EnjoySR/ESTranslate-Xcode","description":"Xcode代码单词快速翻译","created_at":"2016-05-20 01:05:29 UTC","language":"Objective-C","watchers_count":86,"network_count":9,"daily_watchers_count":59},
{"id":14712850,"full_name":"syncthing/syncthing","html_url":"https://github.com/syncthing/syncthing","description":"Open Source Continuous File Synchronization","created_at":"2013-11-26 09:48:21 UTC","language":"Go","watchers_count":12316,"network_count":941,"daily_watchers_count":57},
{"id":52210728,"full_name":"phodal/growth-ebook","html_url":"https://github.com/phodal/growth-ebook","description":"Growth Engineering: The Definitive Guide。全栈增长工程师指南","created_at":"2016-02-21 14:37:32 UTC","language":"HTML","watchers_count":3312,"network_count":573,"daily_watchers_count":56},
{"id":31158982,"full_name":"3lvis/Networking","html_url":"https://github.com/3lvis/Networking","description":"Simple HTTP Networking in Swift a NSURLSession wrapper with image caching support","created_at":"2015-02-22 09:59:21 UTC","language":"Swift","watchers_count":533,"network_count":24,"daily_watchers_count":54},
{"id":45717250,"full_name":"tensorflow/tensorflow","html_url":"https://github.com/tensorflow/tensorflow","description":"Computation using data flow graphs for scalable machine learning","created_at":"2015-11-07 01:19:20 UTC","language":"C++","watchers_count":24655,"network_count":9349,"daily_watchers_count":53},
{"id":51117837,"full_name":"tensorflow/models","html_url":"https://github.com/tensorflow/models","description":"Models built with TensorFlow","created_at":"2016-02-05 01:15:20 UTC","language":"Python","watchers_count":5169,"network_count":813,"daily_watchers_count":49},
{"id":59428917,"full_name":"benjojo/totp-ssh-fluxer","html_url":"https://github.com/benjojo/totp-ssh-fluxer","description":"Take security by obscurity to the next level","created_at":"2016-05-22 18:55:16 UTC","language":"Go","watchers_count":64,"network_count":0,"daily_watchers_count":48},
{"id":44634390,"full_name":"schollz/find","html_url":"https://github.com/schollz/find","description":"High-precision indoor positioning framework for most wifi-enabled devices.","created_at":"2015-10-20 20:54:32 UTC","language":"Go","watchers_count":3084,"network_count":118,"daily_watchers_count":48},
{"id":59386984,"full_name":"gngeorgiev/jshell","html_url":"https://github.com/gngeorgiev/jshell","description":":computer: A JavaScript based unix shell with pure JavaScript configs","created_at":"2016-05-22 00:06:35 UTC","language":"JavaScript","watchers_count":48,"network_count":0,"daily_watchers_count":47},
{"id":59150440,"full_name":"BalestraPatrick/ParticlesLoadingView","html_url":"https://github.com/BalestraPatrick/ParticlesLoadingView","description":"A customizable SpriteKit particles animation on the border of a view.","created_at":"2016-05-18 20:52:53 UTC","language":"Swift","watchers_count":315,"network_count":10,"daily_watchers_count":47},
{"id":1380117,"full_name":"getlantern/lantern","html_url":"https://github.com/getlantern/lantern","description":":zap: Open Internet for everyone. Lantern is a free desktop application that delivers fast, reliable and secure access to the open Internet for users in censored regions. It uses a variety of techniques to stay unblocked, including P2P and domain fronting. Lantern relies on users in uncensored regions acting as access points to the open Internet.","created_at":"2011-02-17 22:12:29 UTC","language":"Go","watchers_count":15649,"network_count":4059,"daily_watchers_count":46},
{"id":24011030,"full_name":"osrg/gobgp","html_url":"https://github.com/osrg/gobgp","description":"BGP implemented in the Go Programming Language","created_at":"2014-09-14 01:51:58 UTC","language":"Go","watchers_count":782,"network_count":76,"daily_watchers_count":45},
{"id":55409392,"full_name":"Ramotion/preview-transition","html_url":"https://github.com/Ramotion/preview-transition","description":"PreviewTransition is a simple preview gallery controller","created_at":"2016-04-04 12:28:00 UTC","language":"Swift","watchers_count":288,"network_count":16,"daily_watchers_count":43},
{"id":10270250,"full_name":"facebook/react","html_url":"https://github.com/facebook/react","description":"A declarative, efficient, and flexible JavaScript library for building user interfaces.","created_at":"2013-05-24 16:15:54 UTC","language":"JavaScript","watchers_count":42426,"network_count":7202,"daily_watchers_count":43},
{"id":59188008,"full_name":"720kb/checkbox.css","html_url":"https://github.com/720kb/checkbox.css","description":":white_small_square: Tiny set of CSS3 animations for your checkbox input. https://720kb.github.io/checkbox.css","created_at":"2016-05-19 08:26:14 UTC","language":"CSS","watchers_count":145,"network_count":9,"daily_watchers_count":42},
{"id":11730342,"full_name":"vuejs/vue","html_url":"https://github.com/vuejs/vue","description":"Simple yet powerful library for building modern web interfaces.","created_at":"2013-07-29 03:24:51 UTC","language":"JavaScript","watchers_count":19253,"network_count":1923,"daily_watchers_count":42},
{"id":58673385,"full_name":"tbenthompson/cppimport","html_url":"https://github.com/tbenthompson/cppimport","description":"Import C++ files directly from Python!","created_at":"2016-05-12 20:11:40 UTC","language":"Python","watchers_count":446,"network_count":11,"daily_watchers_count":41},
{"id":2126244,"full_name":"twbs/bootstrap","html_url":"https://github.com/twbs/bootstrap","description":"The most popular HTML, CSS, and JavaScript framework for developing responsive, mobile first projects on the web.","created_at":"2011-07-29 21:19:00 UTC","language":"CSS","watchers_count":96314,"network_count":42148,"daily_watchers_count":40},
{"id":58396278,"full_name":"Codeido/PMAlertController","html_url":"https://github.com/Codeido/PMAlertController","description":"PMAlertController is a great and customizable substitute to UIAlertController","created_at":"2016-05-09 17:47:17 UTC","language":"Swift","watchers_count":546,"network_count":26,"daily_watchers_count":39},
{"id":58482213,"full_name":"yoshuawuyts/choo","html_url":"https://github.com/yoshuawuyts/choo","description":":steam_locomotive::train::train::train::train::train: - framework for creating sturdy web applications","created_at":"2016-05-10 17:50:35 UTC","language":"JavaScript","watchers_count":170,"network_count":3,"daily_watchers_count":39},
{"id":54621372,"full_name":"amznlabs/amazon-dsstne","html_url":"https://github.com/amznlabs/amazon-dsstne","description":"Deep Scalable Sparse Tensor Network Engine (DSSTNE) is an Amazon developed library for building Deep Learning (DL) machine learning (ML) models ","created_at":"2016-03-24 06:57:40 UTC","language":"C++","watchers_count":2614,"network_count":375,"daily_watchers_count":38},
{"id":21737465,"full_name":"sindresorhus/awesome","html_url":"https://github.com/sindresorhus/awesome","description":"A curated list of awesome lists","created_at":"2014-07-11 13:42:37 UTC","language":null,"watchers_count":35567,"network_count":3953,"daily_watchers_count":38},
{"id":56408159,"full_name":"ShamylZakariya/StickyHeaders","html_url":"https://github.com/ShamylZakariya/StickyHeaders","description":"Adapter and LayoutManager for Android RecyclerView which enables sticky header positioning.","created_at":"2016-04-16 22:20:07 UTC","language":"Java","watchers_count":245,"network_count":15,"daily_watchers_count":38},
{"id":3148715,"full_name":"reenhanced/gitreflow","html_url":"https://github.com/reenhanced/gitreflow","description":"Reflow automatically creates pull requests, ensures the code review is approved, and squash merges finished branches to master with a great commit message template.","created_at":"2012-01-10 21:15:52 UTC","language":"Ruby","watchers_count":1074,"network_count":47,"daily_watchers_count":37},
{"id":52034309,"full_name":"uber-go/zap","html_url":"https://github.com/uber-go/zap","description":"Fast, structured, leveled logging in Go","created_at":"2016-02-18 19:52:56 UTC","language":"Go","watchers_count":399,"network_count":16,"daily_watchers_count":37},
{"id":43666592,"full_name":"agermanidis/Antipersona","html_url":"https://github.com/agermanidis/Antipersona","description":"Don't be yourself, be everyone else","created_at":"2015-10-05 05:19:53 UTC","language":"Objective-C","watchers_count":50,"network_count":1,"daily_watchers_count":36},
{"id":14440270,"full_name":"getify/You-Dont-Know-JS","html_url":"https://github.com/getify/You-Dont-Know-JS","description":"A book series on JavaScript. @YDKJS on twitter.","created_at":"2013-11-16 02:37:24 UTC","language":"JavaScript","watchers_count":30941,"network_count":4200,"daily_watchers_count":36},
{"id":291137,"full_name":"robbyrussell/oh-my-zsh","html_url":"https://github.com/robbyrussell/oh-my-zsh","description":"A delightful community-driven framework for managing your zsh configuration. Includes 200+ optional plugins (rails, git, OSX, hub, capistrano, brew, ant, php, python, etc), over 140 themes to spice up your morning, and an auto-update tool so that makes it easy to keep up with the latest updates from the community.","created_at":"2009-08-28 18:15:37 UTC","language":"Shell","watchers_count":37366,"network_count":9743,"daily_watchers_count":35},
{"id":51392574,"full_name":"redfin/react-server","html_url":"https://github.com/redfin/react-server","description":"React framework with server render for blazing fast page load and seamless transitions between pages in the browser.","created_at":"2016-02-09 19:20:35 UTC","language":"JavaScript","watchers_count":451,"network_count":28,"daily_watchers_count":35},
{"id":34096,"full_name":"leachim6/hello-world","html_url":"https://github.com/leachim6/hello-world","description":"Hello world in every programming language.  Thanks to everyone who contributes to this, I read all pull requests!","created_at":"2008-07-15 00:15:08 UTC","language":"Assembly","watchers_count":1628,"network_count":598,"daily_watchers_count":34},
{"id":17154573,"full_name":"php-pm/php-pm","html_url":"https://github.com/php-pm/php-pm","description":"PPM is a process manager, supercharger and load balancer for PHP applications.","created_at":"2014-02-24 23:25:40 UTC","language":"PHP","watchers_count":2185,"network_count":112,"daily_watchers_count":33},
{"id":24195339,"full_name":"angular/angular","html_url":"https://github.com/angular/angular","description":"","created_at":"2014-09-18 16:12:01 UTC","language":"TypeScript","watchers_count":12133,"network_count":3168,"daily_watchers_count":33},
{"id":19620844,"full_name":"buunguyen/octotree","html_url":"https://github.com/buunguyen/octotree","description":"Code tree for GitHub and GitLab","created_at":"2014-05-09 18:15:20 UTC","language":"JavaScript","watchers_count":5569,"network_count":391,"daily_watchers_count":33},
{"id":34864402,"full_name":"dmlc/mxnet","html_url":"https://github.com/dmlc/mxnet","description":"Lightweight, Portable, Flexible Distributed/Mobile Deep Learning with Dynamic, Mutation-aware Dataflow Dep Scheduler; for Python, R, Julia, Scala, Go, Javascript and more","created_at":"2015-04-30 16:21:15 UTC","language":"C++","watchers_count":3760,"network_count":1342,"daily_watchers_count":32},
{"id":36535156,"full_name":"reactjs/redux","html_url":"https://github.com/reactjs/redux","description":"Predictable state container for JavaScript apps","created_at":"2015-05-29 23:53:15 UTC","language":"JavaScript","watchers_count":18587,"network_count":2420,"daily_watchers_count":32},
{"id":50056934,"full_name":"twitter/distributedlog","html_url":"https://github.com/twitter/distributedlog","description":"A high performance replicated log service.","created_at":"2016-01-20 20:07:32 UTC","language":"Java","watchers_count":1604,"network_count":134,"daily_watchers_count":32},
{"id":58500595,"full_name":"SimplicityMobile/Simplicity","html_url":"https://github.com/SimplicityMobile/Simplicity","description":"A simple way to implement Facebook and Google login in your iOS and OS X apps.","created_at":"2016-05-10 23:51:08 UTC","language":"Swift","watchers_count":128,"network_count":6,"daily_watchers_count":31},
{"id":49986046,"full_name":"draios/falco","html_url":"https://github.com/draios/falco","description":"Behavioral Activity Monitoring With Container Support","created_at":"2016-01-19 21:58:12 UTC","language":"C++","watchers_count":234,"network_count":10,"daily_watchers_count":31},
{"id":2325298,"full_name":"torvalds/linux","html_url":"https://github.com/torvalds/linux","description":"Linux kernel source tree","created_at":"2011-09-04 22:48:12 UTC","language":"C","watchers_count":32482,"network_count":12833,"daily_watchers_count":31},
{"id":27193779,"full_name":"nodejs/node","html_url":"https://github.com/nodejs/node","description":"Node.js JavaScript runtime :sparkles::turtle::rocket::sparkles:","created_at":"2014-11-26 19:57:11 UTC","language":"JavaScript","watchers_count":23386,"network_count":3331,"daily_watchers_count":31},
{"id":38887351,"full_name":"r-lyeh/scriptorium","html_url":"https://github.com/r-lyeh/scriptorium","description":":scroll: Game Scripting Languages benchmarked","created_at":"2015-07-10 15:23:30 UTC","language":"C","watchers_count":100,"network_count":5,"daily_watchers_count":30},
{"id":57351462,"full_name":"dreamlivemeng/androidstudio-plugins","html_url":"https://github.com/dreamlivemeng/androidstudio-plugins","description":"Android studio 插件","created_at":"2016-04-29 03:21:25 UTC","language":null,"watchers_count":339,"network_count":54,"daily_watchers_count":30},
{"id":59107111,"full_name":"venshine/GoodView","html_url":"https://github.com/venshine/GoodView","description":"Android点赞+1效果，支持文本和图像","created_at":"2016-05-18 10:49:52 UTC","language":"Java","watchers_count":128,"network_count":19,"daily_watchers_count":29},
{"id":56717493,"full_name":"joshbuchea/HEAD","html_url":"https://github.com/joshbuchea/HEAD","description":"A list of everything that goes in the <head> of your document","created_at":"2016-04-20 20:05:37 UTC","language":null,"watchers_count":8242,"network_count":440,"daily_watchers_count":28},
{"id":56924966,"full_name":"mr5/icarus-android","html_url":"https://github.com/mr5/icarus-android","description":"The best rich text editor for android platform, which includes more completely features. 安卓富文本编辑器","created_at":"2016-04-23 15:00:51 UTC","language":"JavaScript","watchers_count":242,"network_count":23,"daily_watchers_count":28},
{"id":45456804,"full_name":"jobbole/awesome-python-cn","html_url":"https://github.com/jobbole/awesome-python-cn","description":"Python资源大全中文版，内容包括：Web框架、网络爬虫、网络内容提取、模板引擎、数据库、数据可视化、图片处理、文本处理、自然语言处理、机器学习、日志、代码分析等","created_at":"2015-11-03 09:50:50 UTC","language":null,"watchers_count":1542,"network_count":503,"daily_watchers_count":28},
{"id":46629305,"full_name":"NARKOZ/hacker-scripts","html_url":"https://github.com/NARKOZ/hacker-scripts","description":"Based on a true story","created_at":"2015-11-21 19:05:09 UTC","language":"JavaScript","watchers_count":22265,"network_count":4039,"daily_watchers_count":28},
{"id":23096959,"full_name":"golang/go","html_url":"https://github.com/golang/go","description":"The Go programming language","created_at":"2014-08-19 04:33:40 UTC","language":"Go","watchers_count":17018,"network_count":2130,"daily_watchers_count":28},
{"id":57999295,"full_name":"mpociot/laravel-apidoc-generator","html_url":"https://github.com/mpociot/laravel-apidoc-generator","description":"Laravel API Documentation Generator","created_at":"2016-05-03 20:20:16 UTC","language":"PHP","watchers_count":154,"network_count":10,"daily_watchers_count":27},
{"id":57602929,"full_name":"open-power-workgroup/Hospital","html_url":"https://github.com/open-power-workgroup/Hospital","description":"OpenPower工作组收集汇总的医院开放数据","created_at":"2016-05-01 14:59:21 UTC","language":"HTML","watchers_count":4749,"network_count":943,"daily_watchers_count":27},
{"id":58615799,"full_name":"javierbyte/visual-center","html_url":"https://github.com/javierbyte/visual-center","description":"Tool that will find the visual center of your images.","created_at":"2016-05-12 06:51:39 UTC","language":"JavaScript","watchers_count":915,"network_count":24,"daily_watchers_count":27},
{"id":47442408,"full_name":"stephentuso/welcome-android","html_url":"https://github.com/stephentuso/welcome-android","description":"A customizable welcome screen","created_at":"2015-12-05 04:34:06 UTC","language":"Java","watchers_count":129,"network_count":18,"daily_watchers_count":27},
{"id":6452529,"full_name":"rethinkdb/rethinkdb","html_url":"https://github.com/rethinkdb/rethinkdb","description":"The open-source database for the realtime web.","created_at":"2012-10-30 05:37:47 UTC","language":"C++","watchers_count":13782,"network_count":1091,"daily_watchers_count":27},
{"id":34526884,"full_name":"ant-design/ant-design","html_url":"https://github.com/ant-design/ant-design","description":":ant: A design language","created_at":"2015-04-24 15:37:24 UTC","language":"CSS","watchers_count":3844,"network_count":655,"daily_watchers_count":27},
{"id":23974149,"full_name":"Dogfalo/materialize","html_url":"https://github.com/Dogfalo/materialize","description":"Materialize, a CSS Framework based on Material Design","created_at":"2014-09-12 19:35:38 UTC","language":"JavaScript","watchers_count":18688,"network_count":2624,"daily_watchers_count":26},
{"id":56652382,"full_name":"AutoRally/autorally","html_url":"https://github.com/AutoRally/autorally","description":"","created_at":"2016-04-20 03:30:14 UTC","language":"C++","watchers_count":57,"network_count":8,"daily_watchers_count":26},
{"id":15653276,"full_name":"Trinea/android-open-project","html_url":"https://github.com/Trinea/android-open-project","description":"Collect and classify android open source projects 微信公众号：codekk","created_at":"2014-01-05 15:20:15 UTC","language":null,"watchers_count":15902,"network_count":8846,"daily_watchers_count":26},
{"id":41881900,"full_name":"Microsoft/vscode","html_url":"https://github.com/Microsoft/vscode","description":"Visual Studio Code","created_at":"2015-09-03 20:23:38 UTC","language":"TypeScript","watchers_count":14563,"network_count":1859,"daily_watchers_count":26},
{"id":6498492,"full_name":"airbnb/javascript","html_url":"https://github.com/airbnb/javascript","description":"JavaScript Style Guide","created_at":"2012-11-01 23:13:50 UTC","language":"JavaScript","watchers_count":35343,"network_count":6566,"daily_watchers_count":26},
{"id":59398169,"full_name":"dgryski/go-perfbook","html_url":"https://github.com/dgryski/go-perfbook","description":null,"created_at":"2016-05-22 06:21:35 UTC","language":null,"watchers_count":26,"network_count":2,"daily_watchers_count":25},
{"id":45557469,"full_name":"NVIDIA/nvidia-docker","html_url":"https://github.com/NVIDIA/nvidia-docker","description":"Build and run Docker containers leveraging NVIDIA GPUs","created_at":"2015-11-04 18:04:49 UTC","language":"Go","watchers_count":959,"network_count":82,"daily_watchers_count":25},
{"id":9309093,"full_name":"Semantic-Org/Semantic-UI","html_url":"https://github.com/Semantic-Org/Semantic-UI","description":"Semantic is a UI component framework based around useful principles from natural language.","created_at":"2013-04-08 23:32:04 UTC","language":"JavaScript","watchers_count":25481,"network_count":2911,"daily_watchers_count":25},
{"id":50881110,"full_name":"aimacode/aima-python","html_url":"https://github.com/aimacode/aima-python","description":"Python implementation of algorithms from Russell And Norvig's \"Artificial Intelligence - A Modern Approach\"","created_at":"2016-02-02 00:11:19 UTC","language":"Python","watchers_count":434,"network_count":170,"daily_watchers_count":25},
{"id":21289110,"full_name":"vinta/awesome-python","html_url":"https://github.com/vinta/awesome-python","description":"A curated list of awesome Python frameworks, libraries, software and resources","created_at":"2014-06-27 21:00:06 UTC","language":"Python","watchers_count":20985,"network_count":3871,"daily_watchers_count":25},
{"id":1039520,"full_name":"rg3/youtube-dl","html_url":"https://github.com/rg3/youtube-dl","description":"Small command-line program to download videos from YouTube.com and other video sites","created_at":"2010-10-31 14:35:07 UTC","language":"Python","watchers_count":17917,"network_count":3436,"daily_watchers_count":25},
{"id":58605580,"full_name":"garbles/why-did-you-update","html_url":"https://github.com/garbles/why-did-you-update","description":":boom: Puts your console on blast when React is making unnecessary updates.","created_at":"2016-05-12 03:49:06 UTC","language":"JavaScript","watchers_count":1863,"network_count":23,"daily_watchers_count":25},
{"id":3544424,"full_name":"jkbrzt/httpie","html_url":"https://github.com/jkbrzt/httpie","description":"CLI HTTP client, user-friendly curl replacement with intuitive UI, JSON support, syntax highlighting, wget-like downloads, extensions, etc.","created_at":"2012-02-25 12:39:13 UTC","language":"Python","watchers_count":22710,"network_count":1415,"daily_watchers_count":25},
{"id":14106970,"full_name":"tachyons-css/tachyons","html_url":"https://github.com/tachyons-css/tachyons","description":"Functional CSS for humans","created_at":"2013-11-04 10:41:59 UTC","language":"CSS","watchers_count":1580,"network_count":91,"daily_watchers_count":25},
{"id":57951491,"full_name":"chai2010/ptyy","html_url":"https://github.com/chai2010/ptyy","description":"莆田医院: 莆田系 野鸡医院 查询 (iOS/Swift/Go/Ruby/)","created_at":"2016-05-03 07:52:59 UTC","language":"Go","watchers_count":45,"network_count":7,"daily_watchers_count":24},
{"id":943149,"full_name":"d3/d3","html_url":"https://github.com/d3/d3","description":"Bring data to life with SVG, Canvas and HTML. :bar_chart::chart_with_upwards_trend::tada:","created_at":"2010-09-27 17:22:42 UTC","language":"JavaScript","watchers_count":50100,"network_count":13564,"daily_watchers_count":24},
{"id":29268051,"full_name":"google/material-design-lite","html_url":"https://github.com/google/material-design-lite","description":"Material Design Lite Components in HTML/CSS/JS","created_at":"2015-01-14 22:01:33 UTC","language":"HTML","watchers_count":20875,"network_count":3349,"daily_watchers_count":24},
{"id":3470471,"full_name":"FortAwesome/Font-Awesome","html_url":"https://github.com/FortAwesome/Font-Awesome","description":"The iconic font and CSS toolkit","created_at":"2012-02-17 14:19:43 UTC","language":"HTML","watchers_count":42363,"network_count":7240,"daily_watchers_count":24},
{"id":34624870,"full_name":"kaphacius/IconMaker","html_url":"https://github.com/kaphacius/IconMaker","description":"an Xcode plug-in for making app icons","created_at":"2015-04-26 18:23:34 UTC","language":"Swift","watchers_count":293,"network_count":23,"daily_watchers_count":24},
{"id":58396529,"full_name":"FabianTerhorst/FastLayout","html_url":"https://github.com/FabianTerhorst/FastLayout","description":"Generates a Java Object for your xml layout to reduce inflate time to zero","created_at":"2016-05-09 17:51:44 UTC","language":"Java","watchers_count":40,"network_count":0,"daily_watchers_count":23},
{"id":59383293,"full_name":"JamesMilnerUK/quadtree-go","html_url":"https://github.com/JamesMilnerUK/quadtree-go","description":"A Quadtree implemented in Go","created_at":"2016-05-21 22:01:27 UTC","language":"Go","watchers_count":27,"network_count":0,"daily_watchers_count":23},
{"id":29028775,"full_name":"facebook/react-native","html_url":"https://github.com/facebook/react-native","description":"A framework for building native apps with React.","created_at":"2015-01-09 18:10:16 UTC","language":"JavaScript","watchers_count":32517,"network_count":6615,"daily_watchers_count":23},
{"id":56880047,"full_name":"staltz/xstream","html_url":"https://github.com/staltz/xstream","description":"An extremely intuitive, small, and fast functional reactive stream library for JavaScript","created_at":"2016-04-22 19:25:41 UTC","language":"TypeScript","watchers_count":391,"network_count":14,"daily_watchers_count":23},
{"id":45261969,"full_name":"nickbutcher/plaid","html_url":"https://github.com/nickbutcher/plaid","description":"","created_at":"2015-10-30 16:10:56 UTC","language":"Java","watchers_count":5024,"network_count":875,"daily_watchers_count":23},
{"id":15204860,"full_name":"papers-we-love/papers-we-love","html_url":"https://github.com/papers-we-love/papers-we-love","description":"Papers from the computer science community to read and discuss.","created_at":"2013-12-15 14:31:41 UTC","language":null,"watchers_count":16399,"network_count":1642,"daily_watchers_count":23},
{"id":65252,"full_name":"jekyll/jekyll","html_url":"https://github.com/jekyll/jekyll","description":":globe_with_meridians: Jekyll is a blog-aware, static site generator in Ruby","created_at":"2008-10-20 06:29:03 UTC","language":"Ruby","watchers_count":25358,"network_count":5490,"daily_watchers_count":23},
{"id":44838949,"full_name":"apple/swift","html_url":"https://github.com/apple/swift","description":"The Swift Programming Language","created_at":"2015-10-23 21:15:07 UTC","language":"C++","watchers_count":30505,"network_count":4155,"daily_watchers_count":23},
{"id":46261404,"full_name":"facebook/reason","html_url":"https://github.com/facebook/reason","description":"A meta language toolchain to build systems rapidly","created_at":"2015-11-16 08:22:32 UTC","language":"OCaml","watchers_count":1238,"network_count":65,"daily_watchers_count":23},
{"id":53877810,"full_name":"facebook/fbctf","html_url":"https://github.com/facebook/fbctf","description":"Platform to host Capture the Flag competitions","created_at":"2016-03-14 17:42:04 UTC","language":"Hack","watchers_count":3966,"network_count":637,"daily_watchers_count":22},
{"id":237159,"full_name":"expressjs/express","html_url":"https://github.com/expressjs/express","description":"Fast, unopinionated, minimalist web framework for node.","created_at":"2009-06-26 18:56:01 UTC","language":"JavaScript","watchers_count":25265,"network_count":4756,"daily_watchers_count":22},
{"id":47071941,"full_name":"yelouafi/redux-saga","html_url":"https://github.com/yelouafi/redux-saga","description":"An alternative side effect model for Redux apps","created_at":"2015-11-29 16:58:12 UTC","language":"JavaScript","watchers_count":2433,"network_count":155,"daily_watchers_count":22},
{"id":1062897,"full_name":"github/gitignore","html_url":"https://github.com/github/gitignore","description":"A collection of useful .gitignore templates","created_at":"2010-11-08 20:17:14 UTC","language":null,"watchers_count":36713,"network_count":14038,"daily_watchers_count":22},
{"id":28723659,"full_name":"ChristosChristofidis/awesome-deep-learning","html_url":"https://github.com/ChristosChristofidis/awesome-deep-learning","description":"A curated list of awesome Deep Learning tutorials, projects and communities.","created_at":"2015-01-02 19:28:35 UTC","language":null,"watchers_count":2042,"network_count":569,"daily_watchers_count":22},
{"id":45431898,"full_name":"bvaughn/react-virtualized","html_url":"https://github.com/bvaughn/react-virtualized","description":"React components for efficiently rendering large lists and tabular data","created_at":"2015-11-03 00:48:07 UTC","language":"JavaScript","watchers_count":1942,"network_count":99,"daily_watchers_count":22},
{"id":50603846,"full_name":"ParsePlatform/parse-server","html_url":"https://github.com/ParsePlatform/parse-server","description":"Parse-compatible API server module for Node/Express","created_at":"2016-01-28 18:29:14 UTC","language":"JavaScript","watchers_count":9408,"network_count":2309,"daily_watchers_count":22},
{"id":52677592,"full_name":"jtoy/awesome-tensorflow","html_url":"https://github.com/jtoy/awesome-tensorflow","description":"TensorFlow - A curated list of dedicated resources http://tensorflow.org","created_at":"2016-02-27 17:00:27 UTC","language":null,"watchers_count":2567,"network_count":205,"daily_watchers_count":22},
{"id":19983755,"full_name":"izzyleung/ZhihuDailyPurify","html_url":"https://github.com/izzyleung/ZhihuDailyPurify","description":"Purified version of Zhihu Daily - 更纯净的知乎日报","created_at":"2014-05-20 14:19:41 UTC","language":"Java","watchers_count":2045,"network_count":550,"daily_watchers_count":21},
{"id":56829007,"full_name":"iCHAIT/awesome-subreddits","html_url":"https://github.com/iCHAIT/awesome-subreddits","description":"A curated list of awesome programming subreddits.","created_at":"2016-04-22 05:38:29 UTC","language":null,"watchers_count":113,"network_count":3,"daily_watchers_count":21},
{"id":26516210,"full_name":"certbot/certbot","html_url":"https://github.com/certbot/certbot","description":"Certbot, previously the Let's Encrypt Client, is EFF's tool to obtain certs from Let's Encrypt, and (optionally) autoenable HTTPS on your server.  It can also act as a client for any other CA that uses the ACME protocol.","created_at":"2014-11-12 02:52:20 UTC","language":"Python","watchers_count":15045,"network_count":1190,"daily_watchers_count":21},
{"id":55973577,"full_name":"LibreVR/Revive","html_url":"https://github.com/LibreVR/Revive","description":"Play Oculus exclusive games on the HTC Vive, scroll down for downloads and installation instructions. Please forward all donations to the EFF.","created_at":"2016-04-11 13:12:23 UTC","language":"C++","watchers_count":599,"network_count":78,"daily_watchers_count":21},
{"id":10788737,"full_name":"codepath/android_guides","html_url":"https://github.com/codepath/android_guides","description":"Extensive Open-Source Guides for Android Developers","created_at":"2013-06-19 10:24:45 UTC","language":null,"watchers_count":12495,"network_count":3030,"daily_watchers_count":21},
{"id":18840003,"full_name":"kriasoft/react-starter-kit","html_url":"https://github.com/kriasoft/react-starter-kit","description":"React Starter Kit — isomorphic web app boilerplate (Node.js, Express, GraphQL, React.js, Babel 6, PostCSS, Webpack, Browsersync)","created_at":"2014-04-16 13:08:18 UTC","language":"JavaScript","watchers_count":8427,"network_count":1588,"daily_watchers_count":21},
{"id":54492045,"full_name":"blockchain/thunder","html_url":"https://github.com/blockchain/thunder","description":"Off-Chain Bitcoin payments using smart contracts ","created_at":"2016-03-22 16:43:04 UTC","language":"Java","watchers_count":168,"network_count":27,"daily_watchers_count":21},
{"id":22670857,"full_name":"enaqx/awesome-react","html_url":"https://github.com/enaqx/awesome-react","description":"A collection of awesome things regarding React ecosystem.","created_at":"2014-08-06 05:31:44 UTC","language":"JavaScript","watchers_count":13518,"network_count":1248,"daily_watchers_count":21},
{"id":58894411,"full_name":"testdouble/test-smells","html_url":"https://github.com/testdouble/test-smells","description":"A workbook repository of example test smells and what to do about them.","created_at":"2016-05-16 01:30:39 UTC","language":"JavaScript","watchers_count":29,"network_count":0,"daily_watchers_count":21},
{"id":14434734,"full_name":"devttys0/binwalk","html_url":"https://github.com/devttys0/binwalk","description":"Firmware Analysis Tool","created_at":"2013-11-15 20:45:40 UTC","language":"Python","watchers_count":1658,"network_count":267,"daily_watchers_count":21},
{"id":3214406,"full_name":"meteor/meteor","html_url":"https://github.com/meteor/meteor","description":"Meteor, the JavaScript App Platform","created_at":"2012-01-19 01:58:17 UTC","language":"JavaScript","watchers_count":33942,"network_count":4169,"daily_watchers_count":21},
{"id":55705803,"full_name":"delba/TextAttributes","html_url":"https://github.com/delba/TextAttributes","description":"An easier way to compose attributed strings","created_at":"2016-04-07 15:25:50 UTC","language":"Swift","watchers_count":1535,"network_count":47,"daily_watchers_count":20},
{"id":56013156,"full_name":"kiteco/plugins","html_url":"https://github.com/kiteco/plugins","description":"Editor plugins for Kite","created_at":"2016-04-11 22:42:13 UTC","language":"Java","watchers_count":982,"network_count":80,"daily_watchers_count":20},
{"id":13491895,"full_name":"vhf/free-programming-books","html_url":"https://github.com/vhf/free-programming-books","description":":books: Freely available programming books","created_at":"2013-10-11 06:50:37 UTC","language":null,"watchers_count":55215,"network_count":13028,"daily_watchers_count":20},
{"id":167174,"full_name":"jquery/jquery","html_url":"https://github.com/jquery/jquery","description":"jQuery JavaScript Library","created_at":"2009-04-03 15:20:14 UTC","language":"JavaScript","watchers_count":39500,"network_count":10591,"daily_watchers_count":20},
{"id":53021153,"full_name":"baihui212/tsharding","html_url":"https://github.com/baihui212/tsharding","description":"TSharding is the simple sharding component used in mogujie trade platform.","created_at":"2016-03-03 04:44:16 UTC","language":"Java","watchers_count":61,"network_count":38,"daily_watchers_count":20},
{"id":51148780,"full_name":"googlesamples/android-architecture","html_url":"https://github.com/googlesamples/android-architecture","description":"A collection of samples to discuss and showcase different architectural tools and patterns for Android apps.","created_at":"2016-02-05 13:42:07 UTC","language":null,"watchers_count":6615,"network_count":1267,"daily_watchers_count":20},
{"id":8843683,"full_name":"chartjs/Chart.js","html_url":"https://github.com/chartjs/Chart.js","description":"Simple HTML5 Charts using the <canvas> tag","created_at":"2013-03-17 23:56:36 UTC","language":"JavaScript","watchers_count":22599,"network_count":6262,"daily_watchers_count":20},
{"id":3228505,"full_name":"atom/atom","html_url":"https://github.com/atom/atom","description":"The hackable text editor","created_at":"2012-01-20 18:18:21 UTC","language":"CoffeeScript","watchers_count":27755,"network_count":4749,"daily_watchers_count":20},
{"id":19057465,"full_name":"Uberi/speech_recognition","html_url":"https://github.com/Uberi/speech_recognition","description":"Speech recognition module for Python, supporting several engines and APIs, online and offline.","created_at":"2014-04-23 04:53:54 UTC","language":"Python","watchers_count":894,"network_count":241,"daily_watchers_count":20},
{"id":24841635,"full_name":"date-fns/date-fns","html_url":"https://github.com/date-fns/date-fns","description":"Modern JavaScript date utility library","created_at":"2014-10-06 10:24:22 UTC","language":"JavaScript","watchers_count":697,"network_count":23,"daily_watchers_count":20},
{"id":35658863,"full_name":"puikinsh/gentelella","html_url":"https://github.com/puikinsh/gentelella","description":"Free Bootstrap 3 Admin Template","created_at":"2015-05-15 06:57:27 UTC","language":"HTML","watchers_count":5414,"network_count":1220,"daily_watchers_count":20},
{"id":58034548,"full_name":"google/flexbox-layout","html_url":"https://github.com/google/flexbox-layout","description":"Flexbox for Android ","created_at":"2016-05-04 08:11:22 UTC","language":"Java","watchers_count":3880,"network_count":319,"daily_watchers_count":20},
{"id":24560307,"full_name":"babel/babel","html_url":"https://github.com/babel/babel","description":":tropical_fish: Babel is a compiler for writing next generation JavaScript.","created_at":"2014-09-28 13:38:23 UTC","language":"JavaScript","watchers_count":15694,"network_count":1100,"daily_watchers_count":20},
{"id":7691631,"full_name":"docker/docker","html_url":"https://github.com/docker/docker","description":"Docker - the open-source application container engine","created_at":"2013-01-18 18:10:57 UTC","language":"Go","watchers_count":31427,"network_count":8953,"daily_watchers_count":20},
{"id":55808787,"full_name":"openthread/openthread","html_url":"https://github.com/openthread/openthread","description":"OpenThread is an open-source implementation of the Thread networking protocol","created_at":"2016-04-08 20:47:41 UTC","language":"C++","watchers_count":675,"network_count":111,"daily_watchers_count":20},
{"id":58961022,"full_name":"KrakenDev/PrediKit","html_url":"https://github.com/KrakenDev/PrediKit","description":"An NSPredicate DSL for iOS & OS X inspired by SnapKit and written in Swift","created_at":"2016-05-16 19:30:45 UTC","language":"Swift","watchers_count":222,"network_count":7,"daily_watchers_count":20},
{"id":460078,"full_name":"angular/angular.js","html_url":"https://github.com/angular/angular.js","description":"HTML enhanced for web apps","created_at":"2010-01-06 00:34:37 UTC","language":"JavaScript","watchers_count":49408,"network_count":23762,"daily_watchers_count":20},
{"id":50673771,"full_name":"salsita/redux-elm","html_url":"https://github.com/salsita/redux-elm","description":"The Elm Architecture in JavaScript http://salsita.github.io/redux-elm/","created_at":"2016-01-29 16:10:28 UTC","language":"JavaScript","watchers_count":185,"network_count":5,"daily_watchers_count":20},
{"id":576201,"full_name":"mrdoob/three.js","html_url":"https://github.com/mrdoob/three.js","description":"JavaScript 3D library.","created_at":"2010-03-23 18:58:01 UTC","language":"JavaScript","watchers_count":25175,"network_count":8366,"daily_watchers_count":20},
{"id":55763295,"full_name":"akveo/blur-admin","html_url":"https://github.com/akveo/blur-admin","description":"Angular Bootstrap Admin Panel Framework","created_at":"2016-04-08 08:30:20 UTC","language":"JavaScript","watchers_count":2932,"network_count":387,"daily_watchers_count":20}
]
